istvan/__init__.py
istvan/main.py
istvan-2.0.dist-info/METADATA
istvan-2.0.dist-info/WHEEL
istvan-2.0.dist-info/top_level.txt
istvan-2.0.dist-info/RECORD
