Metadata-Version: 2.1
Name: istvan
Version: 2.0
Summary: A description of your package
Home-page: https://github.com/pista1125/pityu
Author: Istvan
Author-email: pista1125@gmail.com
License: MIT
